mush_lang/mush_lang.py
mush_lang/tools/cli.py
mush_lang-0.0.1.dist-info/METADATA
mush_lang-0.0.1.dist-info/WHEEL
mush_lang-0.0.1.dist-info/entry_points.txt
mush_lang-0.0.1.dist-info/top_level.txt
mush_lang-0.0.1.dist-info/RECORD
